{
  "20260401": {
    "url": "https://www.bing.com/th?id=OHR.WildflowerValley_JA-JP7238318324_1920x1080.jpg",
    "date": "2026-04-01",
    "title": "丘陵を染める一面の野生花",
    "copyright": "セントラル・バレー, 米国 カリフォルニア州 (© Jeff Lewis/Tandem Stills + Motion)",
    "copyrightlink": "https://www.bing.com/search?q=%E3%82%BB%E3%83%B3%E3%83%88%E3%83%A9%E3%83%AB%E3%83%BB%E3%83%90%E3%83%AC%E3%83%BC&form=hpcapt&filters=HpDate%3a%2220260331_1500%22"
  },
  "20260402": {
    "url": "https://www.bing.com/th?id=OHR.MagnoliaBloom2026_JA-JP8135720992_1920x1080.jpg",
    "date": "2026-04-02",
    "title": "春を告げる紫の花",
    "copyright": "シモクレン (© Aflo Co., Ltd./Alamy)",
    "copyrightlink": "https://www.bing.com/search?q=%E3%82%B7%E3%83%A2%E3%82%AF%E3%83%AC%E3%83%B3&form=hpcapt&filters=HpDate%3a%2220260401_1500%22"
  },
  "20260403": {
    "url": "https://www.bing.com/th?id=OHR.ArmbrugBridge_JA-JP3428221440_1920x1080.jpg",
    "date": "2026-04-03",
    "title": "静かな運河に映る街並み",
    "copyright": "アルムブルグ橋, オランダ (© Alexander Spatari/Getty Images)",
    "copyrightlink": "https://www.bing.com/search?q=%E3%82%A2%E3%83%AB%E3%83%A0%E3%83%96%E3%83%AB%E3%82%B0%E6%A9%8B&form=hpcapt&filters=HpDate%3a%2220260402_1500%22"
  }
}